[
  {
    "tags": "Belgium",
    "name": "City Music",
    "url": "http://stream.intronic.nl/citymusic",
    "logo": ""
  },
  {
    "tags": "Belgium",
    "name": "Goeiedagradio 105.1 FM",
    "url": "https://goeiedag.radiostudio.be/aalst",
    "logo": ""
  },
  {
    "tags": "Belgium",
    "name": "Studio Ajoin",
    "url": "http://stream.intronic.nl/ajoinmusic",
    "logo": ""
  },
  {
    "tags": "Belgium",
    "name": "Komilfoo FM 106.9",
    "url": "http://5.63.151.52/proxy/mbogae00?mp=/;stream.mp3",
    "logo": ""
  },
  {
    "tags": "Belgium",
    "name": "MooyZo FM 107.1",
    "url": "http://5.255.85.19/mooyzo",
    "logo": ""
  },
  {
    "tags": "Belgium",
    "name": "Frequence Plus Andenne FM 106.6",
    "url": "http://frequenceplusandenne.ice.infomaniak.ch/frequenceplusandenne-192.mp3",
    "logo": ""
  },
  {
    "tags": "Belgium",
    "name": "Webradioexpress.be",
    "url": "https://s3.radio.co/s3a3e2e82b/listen",
    "logo": ""
  },
  {
    "tags": "Belgium",
    "name": "AudioDrama Radio",
    "url": "http://frits.servebeer.com:8000/stream",
    "logo": ""
  },
  {
    "tags": "Belgium",
    "name": "C-Dance Retro",
    "url": "http://s45.myradiostream.com:18304/;",
    "logo": ""
  },
  {
    "tags": "Belgium",
    "name": "Crooze FM",
    "url": "http://streams.crooze.fm:8400/;",
    "logo": ""
  },
  {
    "tags": "Belgium",
    "name": "Jouwradio",
    "url": "http://82.94.204.71/?.mp3",
    "logo": ""
  },
  {
    "tags": "Belgium",
    "name": "Maeva",
    "url": "http://341.cloudrad.io:8598/live",
    "logo": ""
  },
  {
    "tags": "Belgium",
    "name": "Nostalgie Extra",
    "url": "https://playerservices.streamtheworld.com/api/livestream-redirect/NOSTALGIEWAFEXTRA.mp3?dist=radio_garden",
    "logo": ""
  },
  {
    "tags": "Belgium",
    "name": "Nostalgie Extra - New Wave",
    "url": "https://playerservices.streamtheworld.com/api/livestream-redirect/NOSTALGIEWAFNEWWAVE.mp3?dist=radio_garden",
    "logo": ""
  },
  {
    "tags": "Belgium",
    "name": "Nostalgie Extra - NLtalig",
    "url": "https://playerservices.streamtheworld.com/api/livestream-redirect/NOSTALGIEWAFNL.mp3?dist=radio_garden",
    "logo": ""
  },
  {
    "tags": "Belgium",
    "name": "Nostalgie Extra - Party",
    "url": "https://playerservices.streamtheworld.com/api/livestream-redirect/NOSTALGIEWAFPARTY.mp3?dist=radio_garden",
    "logo": ""
  },
  {
    "tags": "Belgium",
    "name": "Nostalgie Extra - Relax",
    "url": "https://playerservices.streamtheworld.com/api/livestream-redirect/NOSTALGIEWAFRELAX.mp3?dist=radio_garden",
    "logo": ""
  },
  {
    "tags": "Belgium",
    "name": "Nostalgie Extra - Rock",
    "url": "https://playerservices.streamtheworld.com/api/livestream-redirect/NOSTALGIEWAFROCKS.mp3?dist=radio_garden",
    "logo": ""
  },
  {
    "tags": "Belgium",
    "name": "Nostalgie Extra 60 - 70",
    "url": "https://playerservices.streamtheworld.com/api/livestream-redirect/NOSTALGIEWAF6070.mp3?dist=radio_garden",
    "logo": ""
  },
  {
    "tags": "Belgium",
    "name": "Nostalgie Extra 80",
    "url": "https://playerservices.streamtheworld.com/api/livestream-redirect/NOSTALGIEWAF80.mp3?dist=radio_garden",
    "logo": ""
  },
  {
    "tags": "Belgium",
    "name": "Nostalgie Extra 90",
    "url": "https://playerservices.streamtheworld.com/api/livestream-redirect/NOSTALGIEWAF90.mp3?dist=radio_garden",
    "logo": ""
  },
  {
    "tags": "Belgium",
    "name": "Nostalgie Vlaanderen",
    "url": "https://playerservices.streamtheworld.com/api/livestream-redirect/NOSTALGIEWHATAFEELING.mp3?dist=radio_garden",
    "logo": ""
  },
  {
    "tags": "Belgium",
    "name": "NRJ België",
    "url": "https://playerservices.streamtheworld.com/api/livestream-redirect/NRJBELGIE.mp3?dist=radio-garden",
    "logo": ""
  },
  {
    "tags": "Belgium",
    "name": "Radio Centraal 106.7",
    "url": "http://streams.movemedia.eu/centraal",
    "logo": ""
  },
  {
    "tags": "Belgium",
    "name": "Radio FG",
    "url": "http://radiofg.impek.com:80/fga",
    "logo": ""
  },
  {
    "tags": "Belgium",
    "name": "Radio Minerva",
    "url": "http://icecast.movemedia.eu/minerva",
    "logo": ""
  },
  {
    "tags": "Belgium",
    "name": "Radio Park FM",
    "url": "https://streams.movemedia.eu/parkfm",
    "logo": ""
  },
  {
    "tags": "Belgium",
    "name": "Radio Stad",
    "url": "http://stream2.radiostad.org:8344/;",
    "logo": ""
  },
  {
    "tags": "Belgium",
    "name": "Ratelki",
    "url": "http://icepe8.infomaniak.ch/ratelkiradio-128.mp3",
    "logo": ""
  },
  {
    "tags": "Belgium",
    "name": "Sportpaleis FM",
    "url": "https://sportpaleisfm.live-streams.nl/",
    "logo": ""
  },
  {
    "tags": "Belgium",
    "name": "Story FM",
    "url": "http://82.94.204.95:80/live",
    "logo": ""
  },
  {
    "tags": "Belgium",
    "name": "Studio FM Music",
    "url": "http://studiofmmusic.shoutcaststream.com:8230/;",
    "logo": ""
  },
  {
    "tags": "Belgium",
    "name": "VRT Radio 2 Antwerpen",
    "url": "http://icecast.vrtcdn.be/ra2ant-high.mp3",
    "logo": ""
  },
  {
    "tags": "Belgium",
    "name": "Willy",
    "url": "https://22713.live.streamtheworld.com/WILLY.mp3",
    "logo": ""
  },
  {
    "tags": "Belgium",
    "name": "ARL Radio",
    "url": "http://arlradio.ice.infomaniak.ch/poste01.mp3",
    "logo": ""
  },
  {
    "tags": "Belgium",
    "name": "Nostalgie - 60s",
    "url": "https://streamingp.shoutcast.com/Nostalgie60",
    "logo": ""
  },
  {
    "tags": "Belgium",
    "name": "Nostalgie - 70s",
    "url": "https://streamingp.shoutcast.com/Nostalgie-70",
    "logo": ""
  },
  {
    "tags": "Belgium",
    "name": "Nostalgie - 80s",
    "url": "https://streamingp.shoutcast.com/Nostalgie80",
    "logo": ""
  },
  {
    "tags": "Belgium",
    "name": "Nostalgie - 90s",
    "url": "https://streamingp.shoutcast.com/Nostalgie90",
    "logo": ""
  },
  {
    "tags": "Belgium",
    "name": "Nostalgie - Camping",
    "url": "https://streamingp.shoutcast.com/gen4",
    "logo": ""
  },
  {
    "tags": "Belgium",
    "name": "Nostalgie - Chansons Françaises",
    "url": "https://streamingp.shoutcast.com/NostalgieChansonsFrancaises",
    "logo": ""
  },
  {
    "tags": "Belgium",
    "name": "Nostalgie - Cinema",
    "url": "https://streamingp.shoutcast.com/NostalgieCinema",
    "logo": ""
  },
  {
    "tags": "Belgium",
    "name": "Nostalgie - Dance 80s",
    "url": "https://streamingp.shoutcast.com/NostalgieDance80",
    "logo": ""
  },
  {
    "tags": "Belgium",
    "name": "Nostalgie - Dance 90s",
    "url": "https://streamingp.shoutcast.com/NostalgieDance90",
    "logo": ""
  },
  {
    "tags": "Belgium",
    "name": "Nostalgie - Italia",
    "url": "https://streamingp.shoutcast.com/NostalgieItalia-aac",
    "logo": ""
  },
  {
    "tags": "Belgium",
    "name": "Nostalgie - Jazz",
    "url": "https://streamingp.shoutcast.com/NostalgieJazz",
    "logo": ""
  },
  {
    "tags": "Belgium",
    "name": "Nostalgie - Johnny Hallyday",
    "url": "https://streamingp.shoutcast.com/NostalgieJohnnyHallyday",
    "logo": ""
  },
  {
    "tags": "Belgium",
    "name": "Nostalgie - Le Meilleur de Nostalgie",
    "url": "https://streamingp.shoutcast.com/NostalgieLeMeilleur-aac",
    "logo": ""
  },
  {
    "tags": "Belgium",
    "name": "Nostalgie - Love",
    "url": "https://streamingp.shoutcast.com/NostalgieLove",
    "logo": ""
  },
  {
    "tags": "Belgium",
    "name": "Nostalgie - New Wave",
    "url": "https://streamingp.shoutcast.com/NostalgieNewWave",
    "logo": ""
  },
  {
    "tags": "Belgium",
    "name": "Nostalgie - Pop 80",
    "url": "https://streamingp.shoutcast.com/NostalgiePop80",
    "logo": ""
  },
  {
    "tags": "Belgium",
    "name": "Nostalgie - Pop 90",
    "url": "https://streamingp.shoutcast.com/NostalgiePop90",
    "logo": ""
  },
  {
    "tags": "Belgium",
    "name": "Nostalgie - Rock 80",
    "url": "https://streamingp.shoutcast.com/NostalgieRock80",
    "logo": ""
  },
  {
    "tags": "Belgium",
    "name": "Nostalgie - Rock 90",
    "url": "https://streamingp.shoutcast.com/NostalgieRock90",
    "logo": ""
  },
  {
    "tags": "Belgium",
    "name": "Nostalgie - Rock Classics",
    "url": "https://streamingp.shoutcast.com/NostalgieRockClassics",
    "logo": ""
  },
  {
    "tags": "Belgium",
    "name": "Nostalgie - Soul Party",
    "url": "https://streamingp.shoutcast.com/NostalgieSoulparty",
    "logo": ""
  },
  {
    "tags": "Belgium",
    "name": "RTBF Vivacité Luxembourg",
    "url": "https://radios.rtbf.be/vivalux-128.mp3",
    "logo": ""
  },
  {
    "tags": "Belgium",
    "name": "Max FM",
    "url": "http://ks393340.kimsufi.com:9290/;",
    "logo": ""
  },
  {
    "tags": "Belgium",
    "name": "Radio BaHeNa FM 106.7",
    "url": "http://stream.bahena.be:8000/bahena.mp3",
    "logo": ""
  },
  {
    "tags": "Belgium",
    "name": "Nuts Radio",
    "url": "https://www.radioking.com/play/nuts-radio",
    "logo": ""
  },
  {
    "tags": "Belgium",
    "name": "Organroxx",
    "url": "http://radio.organroxx.com:8000/freestream.mp3",
    "logo": ""
  },
  {
    "tags": "Belgium",
    "name": "Mi Amigo 40",
    "url": "https://s19.myradiostream.com/18068/listen.mp3",
    "logo": ""
  },
  {
    "tags": "Belgium",
    "name": "Radio Emotion FM 104.9",
    "url": "http://87.98.189.101/;",
    "logo": ""
  },
  {
    "tags": "Belgium",
    "name": "Radio Park FM",
    "url": "http://streams.movemedia.eu:8000/parkfm",
    "logo": ""
  },
  {
    "tags": "Belgium",
    "name": "Radio Roya",
    "url": "http://46.17.3.52:8397/roya4",
    "logo": ""
  },
  {
    "tags": "Belgium",
    "name": "Trans World Radio",
    "url": "https://twrbe.out.airtime.pro/twrbe_a",
    "logo": ""
  },
  {
    "tags": "Belgium",
    "name": "VBRO",
    "url": "http://stream.vbro.be:9100/vbro",
    "logo": ""
  },
  {
    "tags": "Belgium",
    "name": "Villa Bota",
    "url": "https://caster04.streampakket.com/proxy/8186/stream",
    "logo": ""
  },
  {
    "tags": "Belgium",
    "name": "VRT Radio 2 West-Vlaanderen",
    "url": "http://icecast.vrtcdn.be/ra2wvl-high.mp3",
    "logo": ""
  },
  {
    "tags": "Belgium",
    "name": "2bfm",
    "url": "https://igor.torontocast.com:1560/stream",
    "logo": ""
  },
  {
    "tags": "Belgium",
    "name": "Air Libre 87.7 FM",
    "url": "https://streaming.domainepublic.net/radioairlibre.mp3",
    "logo": ""
  },
  {
    "tags": "Belgium",
    "name": "AraBel FM 106.8",
    "url": "http://www.arabelfm.ice.infomaniak.ch/arabelprodcastfm.mp3",
    "logo": ""
  },
  {
    "tags": "Belgium",
    "name": "Bel RTL",
    "url": "http://audiostream.rtl.be/belrtl128",
    "logo": ""
  },
  {
    "tags": "Belgium",
    "name": "BRUZZ 98.8 FM",
    "url": "http://rrr.sz.xlcdn.com/?account=fmbrussel&file=BRUZZ_HQ&type=live&service=icecast&port=8000&output=m3u",
    "logo": ""
  },
  {
    "tags": "Belgium",
    "name": "BXFM",
    "url": "https://bxfmradio.ice.infomaniak.ch/bxfmradio-192.mp3",
    "logo": ""
  },
  {
    "tags": "Belgium",
    "name": "Cabaret Del Diavolo",
    "url": "https://stream.zeno.fm/ys1shq2k7yzuv",
    "logo": ""
  },
  {
    "tags": "Belgium",
    "name": "Depeche Mode Radio",
    "url": "http://eu2.radioboss.fm:8124/stream?1495181893881.mp3",
    "logo": ""
  },
  {
    "tags": "Belgium",
    "name": "DFR",
    "url": "http://stream-mq.radiodfr.be/",
    "logo": ""
  },
  {
    "tags": "Belgium",
    "name": "DH Radio FM 101.4",
    "url": "https://stream.rcs.revma.com/anew1ctrgzzuv",
    "logo": ""
  },
  {
    "tags": "Belgium",
    "name": "dTER",
    "url": "https://stream-hq.dter.be/",
    "logo": ""
  },
  {
    "tags": "Belgium",
    "name": "Dynamic One",
    "url": "http://stream-hq.dynamicone.be/",
    "logo": ""
  },
  {
    "tags": "Belgium",
    "name": "Farouche",
    "url": "http://178.63.44.94:8000/airtime_128",
    "logo": ""
  },
  {
    "tags": "Belgium",
    "name": "Free Radio",
    "url": "http://freeradiobe.ddns.net:8000/;stream.mp3",
    "logo": ""
  },
  {
    "tags": "Belgium",
    "name": "Fun Radio Belgique",
    "url": "http://funradiobe.ice.infomaniak.ch/funradiobe-high.mp3?.mp3",
    "logo": ""
  },
  {
    "tags": "Belgium",
    "name": "Gold FM 106.1",
    "url": "http://onair.goldfm.be:1061/goldfm.mp3",
    "logo": ""
  },
  {
    "tags": "Belgium",
    "name": "Harmony Radio",
    "url": "http://server1.harmonyradio.be:8000/harmonyradio.mp3",
    "logo": ""
  },
  {
    "tags": "Belgium",
    "name": "Kente FM",
    "url": "https://stream.zeno.fm/zxks2rff8f0uv",
    "logo": ""
  },
  {
    "tags": "Belgium",
    "name": "Kiosk Radio",
    "url": "https://kioskradiobxl.out.airtime.pro/kioskradiobxl_b",
    "logo": ""
  },
  {
    "tags": "Belgium",
    "name": "Klara Continuo",
    "url": "http://icecast.vrtcdn.be/klaracontinuo-high.mp3",
    "logo": ""
  },
  {
    "tags": "Belgium",
    "name": "Musiq3 Beethoven250",
    "url": "https://radios.rtbf.be/wr-pr-m3-128.mp3",
    "logo": ""
  },
  {
    "tags": "Belgium",
    "name": "Nostalgie Belgique",
    "url": "http://streamingp.shoutcast.com/NostalgiePremium",
    "logo": ""
  },
  {
    "tags": "Belgium",
    "name": "NRJ Belgique",
    "url": "https://streamingp.shoutcast.com/NRJ",
    "logo": ""
  },
  {
    "tags": "Belgium",
    "name": "Pure FM",
    "url": "https://radios.rtbf.be/pure-64.aac",
    "logo": ""
  },
  {
    "tags": "Belgium",
    "name": "Radio Alma",
    "url": "http://shoutcast2.wirelessbelgie.be:8310/stream.mp3",
    "logo": ""
  },
  {
    "tags": "Belgium",
    "name": "Radio Campus FM 92.1",
    "url": "https://www.radiocampus.be/stream/stream.aacplus",
    "logo": ""
  },
  {
    "tags": "Belgium",
    "name": "Radio Contact RnB",
    "url": "https://contact2.ice.infomaniak.ch/contact2-192.mp3",
    "logo": ""
  },
  {
    "tags": "Belgium",
    "name": "Radio Judaica Bruxelles",
    "url": "http://radiojudaica.ice.infomaniak.ch/radiojudaica-128",
    "logo": ""
  },
  {
    "tags": "Belgium",
    "name": "Radio Panik",
    "url": "http://streaming.domainepublic.net:8000/radiopanik.mp3",
    "logo": ""
  },
  {
    "tags": "Belgium",
    "name": "Radio Vibration",
    "url": "http://vibrationbelgique.ice.infomaniak.ch:80/vibrationbelgique-high?.mp3",
    "logo": ""
  },
  {
    "tags": "Belgium",
    "name": "ROXX Radio Brussel",
    "url": "http://www.clubfmserver.be:8000/roxx.mp3",
    "logo": ""
  },
  {
    "tags": "Belgium",
    "name": "RTBF Classic 21",
    "url": "https://radios.rtbf.be/classic21-64.aac",
    "logo": ""
  },
  {
    "tags": "Belgium",
    "name": "RTBF Classic 21",
    "url": "https://radios.rtbf.be/classic21-128.mp3",
    "logo": ""
  },
  {
    "tags": "Belgium",
    "name": "RTBF Classic 21 60's",
    "url": "https://radios.rtbf.be/wr-c21-60-128.mp3",
    "logo": ""
  },
  {
    "tags": "Belgium",
    "name": "RTBF Jam",
    "url": "https://radios.rtbf.be/jam-64.aac",
    "logo": ""
  },
  {
    "tags": "Belgium",
    "name": "RTBF La 1ère",
    "url": "https://radios.rtbf.be/laprem1ere-128.mp3",
    "logo": ""
  },
  {
    "tags": "Belgium",
    "name": "RTBF Musiq3",
    "url": "https://radios.rtbf.be/musiq3-128.aac",
    "logo": ""
  },
  {
    "tags": "Belgium",
    "name": "RTBF Pure",
    "url": "https://radios.rtbf.be/pure-128.mp3",
    "logo": ""
  },
  {
    "tags": "Belgium",
    "name": "RTBF Tarmac",
    "url": "https://radios.rtbf.be/tarmac-128.mp3",
    "logo": ""
  },
  {
    "tags": "Belgium",
    "name": "RTBF VivaCité Bruxelles",
    "url": "https://radios.rtbf.be/vivabxl-128.mp3",
    "logo": ""
  },
  {
    "tags": "Belgium",
    "name": "SIS Radio",
    "url": "https://stream.rcs.revma.com/95m12ehhbm0uv.mp3",
    "logo": ""
  },
  {
    "tags": "Belgium",
    "name": "Sunset Radio",
    "url": "http://centova2.whsh4u.com:9028/stream",
    "logo": ""
  },
  {
    "tags": "Belgium",
    "name": "The Word Radio",
    "url": "http://thewordradio.out.airtime.pro:8000/thewordradio_a",
    "logo": ""
  },
  {
    "tags": "Belgium",
    "name": "Viva+",
    "url": "http://radios.rtbf.be/vivaplus-64.aac",
    "logo": ""
  },
  {
    "tags": "Belgium",
    "name": "VRT Ketnet Hits",
    "url": "http://icecast.vrtcdn.be/ketnetradio-high.mp3",
    "logo": ""
  },
  {
    "tags": "Belgium",
    "name": "VRT Klara",
    "url": "http://icecast.vrtcdn.be/klara-high.mp3",
    "logo": ""
  },
  {
    "tags": "Belgium",
    "name": "VRT MNM",
    "url": "http://icecast.vrtcdn.be/mnm-high.mp3",
    "logo": ""
  },
  {
    "tags": "Belgium",
    "name": "VRT MNM Hits",
    "url": "http://icecast.vrtcdn.be/mnm_hits-high.mp3",
    "logo": ""
  },
  {
    "tags": "Belgium",
    "name": "VRT Radio 1",
    "url": "http://icecast.vrtcdn.be/radio1-high.mp3",
    "logo": ""
  },
  {
    "tags": "Belgium",
    "name": "VRT Radio 1 Classics",
    "url": "http://icecast.vrtcdn.be/radio1_classics_high.mp3",
    "logo": ""
  },
  {
    "tags": "Belgium",
    "name": "VRT Radio 2 Vlaams-Brabant",
    "url": "http://icecast.vrtcdn.be/ra2vlb-high.mp3",
    "logo": ""
  },
  {
    "tags": "Belgium",
    "name": "VRT Studio Brussel",
    "url": "http://icecast.vrtcdn.be/stubru-high.mp3",
    "logo": ""
  },
  {
    "tags": "Belgium",
    "name": "VRT Studio Brussel - De Tijdloze",
    "url": "http://icecast.vrtcdn.be/stubru_tijdloze-high.mp3",
    "logo": ""
  },
  {
    "tags": "Belgium",
    "name": "J600",
    "url": "https://streamingv2.shoutcast.com/radio-j600",
    "logo": ""
  },
  {
    "tags": "Belgium",
    "name": "Mixx FM 107.6",
    "url": "http://mixxfm.ice.infomaniak.ch/mixxfm-192.mp3",
    "logo": ""
  },
  {
    "tags": "Belgium",
    "name": "Radio Italia Charleroi",
    "url": "https://str01.fluidstream.net/ric.mp3",
    "logo": ""
  },
  {
    "tags": "Belgium",
    "name": "Radio Quartz",
    "url": "http://91.121.29.128:8026/;",
    "logo": ""
  },
  {
    "tags": "Belgium",
    "name": "RTBF VivaCité Charleroi",
    "url": "https://radios.rtbf.be/vivacharleroi-128.mp3",
    "logo": ""
  },
  {
    "tags": "Belgium",
    "name": "Libellule FM 107.8",
    "url": "https://manager5.streamradio.fr:1665/stream",
    "logo": ""
  },
  {
    "tags": "Belgium",
    "name": "Gaver Omroep FM 105.7",
    "url": "https://s43.myradiostream.com/18192/listen.mp3",
    "logo": ""
  },
  {
    "tags": "Belgium",
    "name": "Radio Tequila 105.1 FM",
    "url": "http://s43.myradiostream.com:20542/listen.mp3",
    "logo": ""
  },
  {
    "tags": "Belgium",
    "name": "TROS FM",
    "url": "http://s16.myradiostream.com:9362/;",
    "logo": ""
  },
  {
    "tags": "Belgium",
    "name": "Radio VRD",
    "url": "http://live.radiostudio.be:8000/vrd",
    "logo": ""
  },
  {
    "tags": "Belgium",
    "name": "Fiesta Radio",
    "url": "https://media1.hostin.cc/fiestaradio.mp3",
    "logo": ""
  },
  {
    "tags": "Belgium",
    "name": "Aktief Gold",
    "url": "http://www.clubfmserver.be:8000/aktief.mp3",
    "logo": ""
  },
  {
    "tags": "Belgium",
    "name": "Club FM",
    "url": "http://www.clubfmserver.be:8000/clubfm.mp3",
    "logo": ""
  },
  {
    "tags": "Belgium",
    "name": "Family Radio",
    "url": "http://www.clubfmserver.be:8000/family.mp3",
    "logo": ""
  },
  {
    "tags": "Belgium",
    "name": "RadioAngel D.C.N.",
    "url": "https://server6.inetcast.nl:1595/stream",
    "logo": ""
  },
  {
    "tags": "Belgium",
    "name": "Frequence Eghezee",
    "url": "http://stream.fr-eghezee.be:8054/FE",
    "logo": ""
  },
  {
    "tags": "Belgium",
    "name": "100,5 Das Hitradio",
    "url": "http://stream.dashitradio.de/dashitradio/mp3-128/?ref=L1St3N",
    "logo": ""
  },
  {
    "tags": "Belgium",
    "name": "BRF1 Radio",
    "url": "https://streaming.brf.be/brf1-high.mp3",
    "logo": ""
  },
  {
    "tags": "Belgium",
    "name": "BRF2 Radio",
    "url": "https://streaming.brf.be/brf2-high.mp3",
    "logo": ""
  },
  {
    "tags": "Belgium",
    "name": "Paradise FM",
    "url": "http://fmradio.hopto.org:7000/",
    "logo": ""
  },
  {
    "tags": "Belgium",
    "name": "Radio Contact Ostbelgien NOW",
    "url": "http://radio-contact.dh-media.net:7000/;",
    "logo": ""
  },
  {
    "tags": "Belgium",
    "name": "Radio Music Sambre",
    "url": "http://radiomusicsambre.ice.infomaniak.ch/radiomusicsambre-128.mp3",
    "logo": ""
  },
  {
    "tags": "Belgium",
    "name": "Néo Radio",
    "url": "http://8500.go2stream.fr:8000/stream",
    "logo": ""
  },
  {
    "tags": "Belgium",
    "name": "Geel FM 107.0",
    "url": "http://geelfm.nsupdate.info:8080/geelfm",
    "logo": ""
  },
  {
    "tags": "Belgium",
    "name": "Radio Internazionale",
    "url": "http://wma07.fluidstream.net:8080/fluid713.aac",
    "logo": ""
  },
  {
    "tags": "Belgium",
    "name": "Radio MIG",
    "url": "http://178.21.16.120:8018/live",
    "logo": ""
  },
  {
    "tags": "Belgium",
    "name": "Radio Superstar",
    "url": "http://178.32.62.163:8411/stream",
    "logo": ""
  },
  {
    "tags": "Belgium",
    "name": "Radio Superstar Classics",
    "url": "https://masterdomains.be:8000/stream/2/",
    "logo": ""
  },
  {
    "tags": "Belgium",
    "name": "Top Radio",
    "url": "https://str.topradio.be/topradio.aac",
    "logo": ""
  },
  {
    "tags": "Belgium",
    "name": "Urgent FM 105.3",
    "url": "http://urgentstream.radiostudio.be:8000/live",
    "logo": ""
  },
  {
    "tags": "Belgium",
    "name": "VRT Radio 2 Oost-Vlaanderen",
    "url": "http://icecast.vrtcdn.be/ra2ovl-high.mp3",
    "logo": ""
  },
  {
    "tags": "Belgium",
    "name": "Zen FM",
    "url": "http://lb.zenfm.be/zenfm.mp3",
    "logo": ""
  },
  {
    "tags": "Belgium",
    "name": "7FM",
    "url": "https://7fm.ice.infomaniak.ch/radio7fm-192.aac",
    "logo": ""
  },
  {
    "tags": "Belgium",
    "name": "Radio 854",
    "url": "https://jenny.torontocast.com:8034/stream",
    "logo": ""
  },
  {
    "tags": "Belgium",
    "name": "Radio PROS",
    "url": "http://live.radiostudio.be/prosaac",
    "logo": ""
  },
  {
    "tags": "Belgium",
    "name": "Radio Victoria",
    "url": "http://shoutcast.radiovictoria.be:8000/;stream/1",
    "logo": ""
  },
  {
    "tags": "Belgium",
    "name": "Stadsradio FM 105.6",
    "url": "http://stadsradiohalle.no-ip.org:8020/;",
    "logo": ""
  },
  {
    "tags": "Belgium",
    "name": "Trendy FM",
    "url": "http://stream.trendyfm.be/;",
    "logo": ""
  },
  {
    "tags": "Belgium",
    "name": "Hasselt1 FM 107.2",
    "url": "http://live.radiostudio.be/hasselt1",
    "logo": ""
  },
  {
    "tags": "Belgium",
    "name": "Versuz Radio",
    "url": "http://versuzradio.live-streams.nl/live",
    "logo": ""
  },
  {
    "tags": "Belgium",
    "name": "VRT Radio 2 Limburg",
    "url": "http://icecast.vrtcdn.be/ra2lim-high.mp3",
    "logo": ""
  },
  {
    "tags": "Belgium",
    "name": "De Goeie Ouwe Tijd",
    "url": "https://16963.live.streamtheworld.com/SAM03AAC392.mp3",
    "logo": ""
  },
  {
    "tags": "Belgium",
    "name": "Magic Radio",
    "url": "http://shoutcast.movemedia.eu/pdgfm",
    "logo": ""
  },
  {
    "tags": "Belgium",
    "name": "Omroep Neteland FM 107.4",
    "url": "https://media1.hostin.cc/omroepneteland.mp3",
    "logo": ""
  },
  {
    "tags": "Belgium",
    "name": "Radio Star 106.5 FM",
    "url": "http://stream.radiostar.be:8000/",
    "logo": ""
  },
  {
    "tags": "Belgium",
    "name": "Sport FM Continu 106.9",
    "url": "https://stream.zeno.fm/kkbcxquzs4zuv",
    "logo": ""
  },
  {
    "tags": "Belgium",
    "name": "Radio 5FM",
    "url": "https://stream.bahena.be/5fm.mp3",
    "logo": ""
  },
  {
    "tags": "Belgium",
    "name": "Radio I.R.O.",
    "url": "http://stadsradio-iro.be:3001/;",
    "logo": ""
  },
  {
    "tags": "Belgium",
    "name": "Radio Totaal FM 105.9",
    "url": "https://live.radiototaal.be/radiototaal-high.mp3",
    "logo": ""
  },
  {
    "tags": "Belgium",
    "name": "Yesterdayland",
    "url": "https://server.yesterdayland.stream/radio/8000/listen",
    "logo": ""
  },
  {
    "tags": "Belgium",
    "name": "Radio Monza",
    "url": "http://stream.intronic.nl/radiomonza",
    "logo": ""
  },
  {
    "tags": "Belgium",
    "name": "Radio Kompas FM 105.8",
    "url": "http://mediaserv33.live-streams.nl:8052/stream",
    "logo": ""
  },
  {
    "tags": "Belgium",
    "name": "FM Kortrijk",
    "url": "https://stream.twinmedia.be:8443/random_stream_path",
    "logo": ""
  },
  {
    "tags": "Belgium",
    "name": "KL85",
    "url": "http://s19.myradiostream.com:18068/listen.mp3",
    "logo": ""
  },
  {
    "tags": "Belgium",
    "name": "Quindo",
    "url": "https://stream.quindo.be/high.mp3",
    "logo": ""
  },
  {
    "tags": "Belgium",
    "name": "Radio 19",
    "url": "https://audiostream.radio19.fm:8200/;",
    "logo": ""
  },
  {
    "tags": "Belgium",
    "name": "Radio MBC",
    "url": "https://listen.radioking.com/radio/181348/stream/223093",
    "logo": ""
  },
  {
    "tags": "Belgium",
    "name": "LRL 106fm",
    "url": "https://live.lokaleradiolanaken.be/",
    "logo": ""
  },
  {
    "tags": "Belgium",
    "name": "Ma Radio FM 90.1",
    "url": "http://maradio2.ice.infomaniak.ch/maradio2-128.mp3",
    "logo": ""
  },
  {
    "tags": "Belgium",
    "name": "Radio Chevauchoir FM 105.5",
    "url": "http://radio10.pro-fhi.net/flux-nqjpklks/stream",
    "logo": ""
  },
  {
    "tags": "Belgium",
    "name": "Radio Maria",
    "url": "http://stream.radiomaria.be:8000/RadioMaria-96",
    "logo": ""
  },
  {
    "tags": "Belgium",
    "name": "Radio Scorpio",
    "url": "http://193.190.253.57:8000/stream",
    "logo": ""
  },
  {
    "tags": "Belgium",
    "name": "Retro Radio Singjaal",
    "url": "http://ice.cr1.streamzilla.xlcdn.com:8000/sz=radiosingjaal=radiostream",
    "logo": ""
  },
  {
    "tags": "Belgium",
    "name": "RGR FM",
    "url": "http://stream.intronic.nl/rgrfm",
    "logo": ""
  },
  {
    "tags": "Belgium",
    "name": "48FM",
    "url": "https://stream.48fm.com:8443/48fm",
    "logo": ""
  },
  {
    "tags": "Belgium",
    "name": "Equinoxe FM",
    "url": "http://equinoxefm.ddns.net:8000/stream.ogg",
    "logo": ""
  },
  {
    "tags": "Belgium",
    "name": "Maximum FM",
    "url": "https://n05a-eu.rcs.revma.com/vnmbzemrmm0uv",
    "logo": ""
  },
  {
    "tags": "Belgium",
    "name": "Radio Prima FM 107.4",
    "url": "http://37.187.114.62:8002/live",
    "logo": ""
  },
  {
    "tags": "Belgium",
    "name": "RTBF Vivacité Liège",
    "url": "https://radios.rtbf.be/vivaliege-64.aac",
    "logo": ""
  },
  {
    "tags": "Belgium",
    "name": "Warm FM",
    "url": "http://stream05.warm.fm:9002/warm",
    "logo": ""
  },
  {
    "tags": "Belgium",
    "name": "Radio Hitalia FM 106.7",
    "url": "http://wma02.fluidstream.net:8130/;stream.nsv",
    "logo": ""
  },
  {
    "tags": "Belgium",
    "name": "Radio Sunshine 97.5 FM",
    "url": "http://streamlive.syndicationradio.fr:8158/stream",
    "logo": ""
  },
  {
    "tags": "Belgium",
    "name": "Radio Maaskant FM 106.7",
    "url": "https://antares.dribbcast.com/proxy/maaskant?mp=/stream",
    "logo": ""
  },
  {
    "tags": "Belgium",
    "name": "Zoe FM",
    "url": "http://shoutcast.movemedia.be/zoe128",
    "logo": ""
  },
  {
    "tags": "Belgium",
    "name": "Mooi Radio",
    "url": "http://mooiradio.live-streams.nl/live",
    "logo": ""
  },
  {
    "tags": "Belgium",
    "name": "Radio Opsinjoor",
    "url": "http://streams.movemedia.eu:8800/;stream/1",
    "logo": ""
  },
  {
    "tags": "Belgium",
    "name": "Radio Reflex",
    "url": "http://shoutcast2.wirelessbelgie.be:8514/;",
    "logo": ""
  },
  {
    "tags": "Belgium",
    "name": "Radio Valencia",
    "url": "http://radiovalenciafm.shoutcaststream.com:8140/stream",
    "logo": ""
  },
  {
    "tags": "Belgium",
    "name": "JessFM 89.9",
    "url": "http://95.85.21.223:8000/;",
    "logo": ""
  },
  {
    "tags": "Belgium",
    "name": "Familieradio Enjoy FM",
    "url": "http://live.radiostudio.be/enjoyfm",
    "logo": ""
  },
  {
    "tags": "Belgium",
    "name": "Radio FM Gold",
    "url": "http://fmgold.mvserver.be:3181/;",
    "logo": ""
  },
  {
    "tags": "Belgium",
    "name": "Melinda FM 107.8",
    "url": "http://vps.melindafm.be:8000/1",
    "logo": ""
  },
  {
    "tags": "Belgium",
    "name": "Radio Gompel",
    "url": "http://caster05.streampakket.com:8916/radiogom",
    "logo": ""
  },
  {
    "tags": "Belgium",
    "name": "Radio Milo",
    "url": "https://centova.zenon.media:8011/stream2.mp3",
    "logo": ""
  },
  {
    "tags": "Belgium",
    "name": "Radio Mol",
    "url": "http://radiomol.ice.infomaniak.ch/radiomol-192.mp3",
    "logo": ""
  },
  {
    "tags": "Belgium",
    "name": "M Radio FM 99.9",
    "url": "http://icepe2.infomaniak.ch/mradio.mp3",
    "logo": ""
  },
  {
    "tags": "Belgium",
    "name": "Phare FM",
    "url": "http://str0.creacast.com:80/pharefm_mons?.mp3",
    "logo": ""
  },
  {
    "tags": "Belgium",
    "name": "RTBF VivaCité Hainaut",
    "url": "https://radios.rtbf.be/vivahainaut-128.mp3",
    "logo": ""
  },
  {
    "tags": "Belgium",
    "name": "YouFM",
    "url": "http://youfm.ice.infomaniak.ch/youfm-96.mp3",
    "logo": ""
  },
  {
    "tags": "Belgium",
    "name": "Planktuin",
    "url": "http://planktone.ddns.net:2500/planktuin",
    "logo": ""
  },
  {
    "tags": "Belgium",
    "name": "RLM FM 107.9",
    "url": "http://philae.shoutca.st:8278/stream",
    "logo": ""
  },
  {
    "tags": "Belgium",
    "name": "RQC 95 FM",
    "url": "http://5.39.80.55:8000/live;",
    "logo": ""
  },
  {
    "tags": "Belgium",
    "name": "Must FM",
    "url": "https://stream.rcs.revma.com/cm96zpmrmm0uv",
    "logo": ""
  },
  {
    "tags": "Belgium",
    "name": "Radio Contact FM 100.4",
    "url": "http://audiostream.rtl.be/contactfr192",
    "logo": ""
  },
  {
    "tags": "Belgium",
    "name": "Radio Equinoxe FM 106.4",
    "url": "http://live.equinoxenamur.be:8000/Equinoxe.mp3",
    "logo": ""
  },
  {
    "tags": "Belgium",
    "name": "RCF Sud Belgique FM 106.8",
    "url": "https://rcf.streamakaci.com/rcfdigital.mp3",
    "logo": ""
  },
  {
    "tags": "Belgium",
    "name": "RTBF VivaCité FM 98.3",
    "url": "https://radios.rtbf.be/vivanamurbw-128.mp3",
    "logo": ""
  },
  {
    "tags": "Belgium",
    "name": "RUN FM 88.1",
    "url": "http://stream.run.be:8000/run128.mp3",
    "logo": ""
  },
  {
    "tags": "Belgium",
    "name": "Radio Beach FM 106.1",
    "url": "https://s47.myradiostream.com/:10592/;",
    "logo": ""
  },
  {
    "tags": "Belgium",
    "name": "Mélodie FM",
    "url": "http://188.165.35.60:8008/;",
    "logo": ""
  },
  {
    "tags": "Belgium",
    "name": "Ultrason",
    "url": "http://ultrason.ice.infomaniak.ch/ultrason-high.mp3",
    "logo": ""
  },
  {
    "tags": "Belgium",
    "name": "RGR FM 107.7 Oostkamp / Brugge",
    "url": "http://www.mvserver.be:3191/;",
    "logo": ""
  },
  {
    "tags": "Belgium",
    "name": "Passion FM 106.5",
    "url": "http://radiopassionfm.ice.infomaniak.ch/radiopassionfm-32.mp3",
    "logo": ""
  },
  {
    "tags": "Belgium",
    "name": "Be One",
    "url": "https://live.radiostudio.be/beone",
    "logo": ""
  },
  {
    "tags": "Belgium",
    "name": "Noordzee 105FM",
    "url": "https://stream.noordzee105.be/noordzee-192",
    "logo": ""
  },
  {
    "tags": "Belgium",
    "name": "Noordzee Info",
    "url": "http://stream.noordzee105.be:8000/noordzee_info",
    "logo": ""
  },
  {
    "tags": "Belgium",
    "name": "Radiostudio Oostende",
    "url": "https://olive.torontocast.com/radio/8090/radio.mp3",
    "logo": ""
  },
  {
    "tags": "Belgium",
    "name": "Radio Antipode",
    "url": "http://streaming.antipode.be:8000/antipode.mp3",
    "logo": ""
  },
  {
    "tags": "Belgium",
    "name": "Radio Noorderkempen Online",
    "url": "http://streams.movemedia.eu:8000/noorderkempen",
    "logo": ""
  },
  {
    "tags": "Belgium",
    "name": "Stereo FM 106.8",
    "url": "http://streams.movemedia.eu:8054/stereofm",
    "logo": ""
  },
  {
    "tags": "Belgium",
    "name": "Radio Benelux",
    "url": "http://remote.radiobenelux.be/MP3",
    "logo": ""
  },
  {
    "tags": "Belgium",
    "name": "FM Goud",
    "url": "https://fmgoud.level27.be/;",
    "logo": ""
  },
  {
    "tags": "Belgium",
    "name": "UpRadio",
    "url": "http://upradio.ovh:8034/;",
    "logo": ""
  },
  {
    "tags": "Belgium",
    "name": "Radio Paloma FM 106",
    "url": "http://84.80.98.187:8000/paloma106",
    "logo": ""
  },
  {
    "tags": "Belgium",
    "name": "Radio Bingo",
    "url": "http://audiostreamen.nl:8044/stream/1/",
    "logo": ""
  },
  {
    "tags": "Belgium",
    "name": "Wradio 106.3 FM",
    "url": "http://stream.wradio.es:9000/index",
    "logo": ""
  },
  {
    "tags": "Belgium",
    "name": "Radio Demerstad",
    "url": "https://stream.radiodemerstad.be/radiodemerstad.mp3",
    "logo": ""
  },
  {
    "tags": "Belgium",
    "name": "Goldies Radio",
    "url": "http://5.63.151.52:7064/stream",
    "logo": ""
  },
  {
    "tags": "Belgium",
    "name": "Radio Land Van Waas",
    "url": "https://stream.rlvw.be/",
    "logo": ""
  },
  {
    "tags": "Belgium",
    "name": "Trudo FM",
    "url": "http://198.143.144.226:8068/stream",
    "logo": ""
  },
  {
    "tags": "Belgium",
    "name": "Radio Quartz FM 93.9",
    "url": "http://manager2.streaming-ingenierie.fr:8026/;",
    "logo": ""
  },
  {
    "tags": "Belgium",
    "name": "Radio Ourthe Amblève",
    "url": "https://roa1062fm.ice.infomaniak.ch/roa1062fm-128.mp3",
    "logo": ""
  },
  {
    "tags": "Belgium",
    "name": "Radio Tamara",
    "url": "http://audiostreamen.nl:8006/;",
    "logo": ""
  },
  {
    "tags": "Belgium",
    "name": "Radio 4910",
    "url": "http://94.23.221.158:9073/stream2",
    "logo": ""
  },
  {
    "tags": "Belgium",
    "name": "Radio Meteor",
    "url": "http://streams.movemedia.eu:8000/meteor",
    "logo": ""
  },
  {
    "tags": "Belgium",
    "name": "Joe - 60's 70's",
    "url": "https://22713.live.streamtheworld.com/JOE_70S.mp3",
    "logo": ""
  },
  {
    "tags": "Belgium",
    "name": "Joe - 80's 90's",
    "url": "https://20723.live.streamtheworld.com/JOE_80S.mp3",
    "logo": ""
  },
  {
    "tags": "Belgium",
    "name": "Joe - Lage Landen",
    "url": "https://20103.live.streamtheworld.com/JOE_LAGE_LANDEN.mp3",
    "logo": ""
  },
  {
    "tags": "Belgium",
    "name": "Joe - Top 2000",
    "url": "https://23603.live.streamtheworld.com/JOE_TOP2000.mp3",
    "logo": ""
  },
  {
    "tags": "Belgium",
    "name": "Joe FM Live",
    "url": "http://icecast-qmusic.cdp.triple-it.nl:80/JOEfm_be_live_128.mp3",
    "logo": ""
  },
  {
    "tags": "Belgium",
    "name": "Qmusic",
    "url": "http://icecast-qmusic.cdp.triple-it.nl/Qmusic_be_live_64.aac?rnd=6891931899801267",
    "logo": ""
  },
  {
    "tags": "Belgium",
    "name": "Waregem1",
    "url": "http://streaming.waregem1.eu/waregem1.mp3",
    "logo": ""
  },
  {
    "tags": "Belgium",
    "name": "RTBF VivaCité Brabant Wallon",
    "url": "http://radios.rtbf.be/vivabw-128.mp3",
    "logo": ""
  },
  {
    "tags": "Belgium",
    "name": "Radio Golden Flash",
    "url": "http://uplink.intronic.nl/goldenflash",
    "logo": ""
  },
  {
    "tags": "Belgium",
    "name": "WFM 105.4",
    "url": "http://178.19.116.3:8094/1",
    "logo": ""
  },
  {
    "tags": "Belgium",
    "name": "Radio Apollo ",
    "url": "http://37.59.195.28:8045/stream",
    "logo": ""
  },
  {
    "tags": "Belgium",
    "name": "Radio Rivierenland FM 104.9",
    "url": "http://randstad.wirelessbelgie.be:8334/;;",
    "logo": ""
  },
  {
    "tags": "Belgium",
    "name": "Radio RSJ",
    "url": "http://cc6.beheerstream.com:8621/;",
    "logo": ""
  },
  {
    "tags": "Belgium",
    "name": "Radio Oost West",
    "url": "http://streams.movemedia.eu:8550/",
    "logo": ""
  },
  {
    "tags": "Belgium",
    "name": "Radio Addictive 50s",
    "url": "http://hazel.torontocast.com:3040/stream",
    "logo": ""
  },
  {
    "tags": "Belgium",
    "name": "Radio Eurodance Classic",
    "url": "http://hazel.torontocast.com:1310/stream",
    "logo": ""
  },
  {
    "tags": "Belgium",
    "name": "RBS Radio FM 107.0",
    "url": "http://luister.rbs-radio.be/rbs",
    "logo": ""
  },
  {
    "tags": "Belgium",
    "name": "Radio M fm",
    "url": "http://149.202.22.75:8248/live",
    "logo": ""
  }
]